{
  "total_bars": 669691,
  "config": {
    "max_support_dist": 0.5,
    "max_resistance_dist": 0.5,
    "min_support_strength": 0.3,
    "min_resistance_strength": 0.3,
    "min_resistance_dist_long": 0.35,
    "min_support_dist_short": 0.35,
    "pos_range_long_max": 0.35,
    "pos_range_short_min": 0.65,
    "ranging_block_long_above": 0.6,
    "ranging_block_short_below": 0.4,
    "sl_buffer_atr": 0.3,
    "sl_floor_atr": 1.0,
    "sl_cap_atr": 2.5,
    "tp_buffer_atr": 0.25,
    "tp_floor_atr": 1.5,
    "tp_cap_atr": 4.0,
    "max_hold_bars": 48,
    "min_rr": 1.2
  },
  "legacy_counts": {
    "short": 145109,
    "flat": 372138,
    "long": 152444
  },
  "gated_counts": {
    "short": 62586,
    "flat": 543683,
    "long": 63422
  },
  "legacy_pct": {
    "short": 21.668,
    "flat": 55.569,
    "long": 22.763
  },
  "gated_pct": {
    "short": 9.346,
    "flat": 81.184,
    "long": 9.47
  },
  "filtered_long": 89022,
  "filtered_short": 82523,
  "long_candidate_pct": 39.344,
  "short_candidate_pct": 42.121,
  "by_regime": {
    "ranging": {
      "bars": 669691,
      "legacy_long": 152444,
      "gated_long": 63422,
      "legacy_short": 145109,
      "gated_short": 62586
    }
  },
  "gate_reasons": {
    "blocked_long": 89022,
    "blocked_short": 82523
  },
  "generated_at": "2026-06-17T19:45:07.270025+00:00",
  "source_npz": "D:\\trae_projects\\ZhuLong3_DevPackage_v2\\data\\clean\\training_horizon_v16_usoil.npz",
  "elapsed_sec": 3.65,
  "replay_cases": [
    {
      "name": "replay_ranging_top_chase_long",
      "note": "震荡高位 legacy long 应被门控为 flat",
      "regime": "ranging",
      "pos_in_range": 0.72,
      "m5_support_dist": 1.2,
      "m5_resistance_dist": 0.25,
      "m5_trend": 0.05,
      "long_candidate": false,
      "short_candidate": true,
      "candidate_stats": {
        "long_candidate": 0,
        "short_candidate": 1,
        "both_candidate": 0
      },
      "verdict": "would_block_long"
    },
    {
      "name": "replay_ranging_bottom_long",
      "note": "震荡低位 long 候选保留",
      "regime": "ranging",
      "pos_in_range": 0.28,
      "m5_support_dist": 0.35,
      "m5_resistance_dist": 1.8,
      "m5_trend": 0.08,
      "long_candidate": true,
      "short_candidate": false,
      "candidate_stats": {
        "long_candidate": 1,
        "short_candidate": 0,
        "both_candidate": 0
      },
      "verdict": "long_candidate"
    }
  ],
  "year_2016": {
    "bars": 62748,
    "legacy_long": 16627,
    "gated_long": 6741,
    "legacy_short": 16429,
    "gated_short": 6680
  },
  "year_2017": {
    "bars": 58719,
    "legacy_long": 10104,
    "gated_long": 4009,
    "legacy_short": 9365,
    "gated_short": 3851
  },
  "year_2018": {
    "bars": 66402,
    "legacy_long": 11317,
    "gated_long": 4612,
    "legacy_short": 11246,
    "gated_short": 4599
  },
  "year_2019": {
    "bars": 64361,
    "legacy_long": 13562,
    "gated_long": 5468,
    "legacy_short": 12293,
    "gated_short": 5223
  },
  "year_2020": {
    "bars": 68827,
    "legacy_long": 20371,
    "gated_long": 8262,
    "legacy_short": 20075,
    "gated_short": 8438
  },
  "year_2021": {
    "bars": 70148,
    "legacy_long": 15914,
    "gated_long": 6193,
    "legacy_short": 14070,
    "gated_short": 5921
  },
  "year_2022": {
    "bars": 70628,
    "legacy_long": 20699,
    "gated_long": 8343,
    "legacy_short": 19361,
    "gated_short": 8135
  },
  "year_2023": {
    "bars": 69746,
    "legacy_long": 14870,
    "gated_long": 6239,
    "legacy_short": 14162,
    "gated_short": 5763
  },
  "year_2024": {
    "bars": 69020,
    "legacy_long": 13199,
    "gated_long": 5491,
    "legacy_short": 12647,
    "gated_short": 5396
  },
  "year_2025": {
    "bars": 69092,
    "legacy_long": 15781,
    "gated_long": 8064,
    "legacy_short": 15461,
    "gated_short": 8580
  }
}